py_g_latin/__init__.py
py_g_latin/converter.py
py_g_latin-0.0.1.dist-info/METADATA
py_g_latin-0.0.1.dist-info/WHEEL
py_g_latin-0.0.1.dist-info/top_level.txt
py_g_latin-0.0.1.dist-info/RECORD
