Metadata-Version: 2.1
Name: py-g-latin
Version: 0.0.1
Summary: My short description
Home-page: https://github.com/alexpnet89
Author: Alex
Author-email: alexpnet89@gmail.com
License: UNKNOWN
Platform: UNKNOWN
Requires-Python: >=3.8
